quicktransfer/__init__.py
quicktransfer/transfer.py
ftransfer-0.1.0.dist-info/METADATA
ftransfer-0.1.0.dist-info/WHEEL
ftransfer-0.1.0.dist-info/entry_points.txt
ftransfer-0.1.0.dist-info/top_level.txt
ftransfer-0.1.0.dist-info/RECORD
