Metadata-Version: 2.2
Name: ftransfer
Version: 0.1.0
Requires-Dist: tqdm
Dynamic: requires-dist
